megalus/__init__.py
megalus/__main__.py
megalus/cmd.py
megalus/main.py
megalus/test_main.py
megalus/test_utils.py
megalus/utils.py
megalus/bash/__init__.py
megalus/bash/commands.py
megalus/bash/test_bash.py
megalus/buildcmd/__init__.py
megalus/buildcmd/commands.py
megalus/buildcmd/test_build.py
megalus/check/__init__.py
megalus/check/commands.py
megalus/check/test_check.py
megalus/commands/__init__.py
megalus/commands/commands.py
megalus/commands/test_commands.py
megalus/compose/__init__.py
megalus/compose/commands.py
megalus/compose/test_compose.py
megalus/down/__init__.py
megalus/down/commands.py
megalus/down/test_down.py
megalus/logscmd/__init__.py
megalus/logscmd/commands.py
megalus/run/__init__.py
megalus/run/commands.py
megalus/run/test_run.py
megalus/start/__init__.py
megalus/start/commands.py
megalus/start/test_start.py
megalus/status/__init__.py
megalus/status/commands.py
megalus/status/dashboard.py
megalus/status/system_watch.py
megalus/stop/__init__.py
megalus/stop/commands.py
megalus/stop/test_stop.py
megalus-5.0.2.dist-info/METADATA
megalus-5.0.2.dist-info/WHEEL
megalus-5.0.2.dist-info/entry_points.txt
megalus-5.0.2.dist-info/top_level.txt
megalus-5.0.2.dist-info/RECORD
