Metadata-Version: 2.1
Name: megalus
Version: 5.0.2
Summary: Command line helpers for docker and docker-compose
Home-page: UNKNOWN
Author: Chris Maillefaud
Author-email: UNKNOWN
License: UNKNOWN
Keywords: aws deploy docker npm redis memcached bash
Platform: UNKNOWN
Classifier: Development Status :: 4 - Beta
Classifier: Intended Audience :: Developers
Classifier: Topic :: Software Development :: Build Tools
Classifier: Programming Language :: Python :: 3.6
Classifier: Programming Language :: Python :: 3.7
Requires-Dist: buzio
Requires-Dist: loguru
Requires-Dist: docker
Requires-Dist: pyyaml
Requires-Dist: click
Requires-Dist: arrow
Requires-Dist: pydashing
Requires-Dist: gitpython
Requires-Dist: tabulate
Requires-Dist: blessed
Requires-Dist: pipenv
Requires-Dist: psutil
